paml_check/__init__.py
paml_check/activity_graph.py
paml_check/constraints.py
paml_check/minimize_duration.py
paml_check/paml_check.py
paml_check/protocol.py
paml_check/timeline.py
paml_check/units.py
paml_check/utils.py
paml_check/convert_constraints/__init__.py
paml_check/convert_constraints/comparison.py
paml_check/convert_constraints/duration.py
paml_check/convert_constraints/expression.py
paml_check/convert_constraints/logic.py
paml_check/convert_constraints/time.py
paml_check-0.1.3.dist-info/LICENSE
paml_check-0.1.3.dist-info/METADATA
paml_check-0.1.3.dist-info/WHEEL
paml_check-0.1.3.dist-info/top_level.txt
paml_check-0.1.3.dist-info/RECORD
