Metadata-Version: 2.1
Name: paml-check
Version: 0.1.3
Summary: PAML Checker
Home-page: https://github.com/SD2E/paml-check
Author: Dan Bryce
Author-email: dbryce@sift.net
License: MIT
Platform: UNKNOWN
License-File: LICENSE
Requires-Dist: pint
Requires-Dist: pysmt
Requires-Dist: sbol3
Requires-Dist: z3-solver
